bbtutils/__init__.py
bbtutils/basicutils.py
bbtutils/httputils.py
bbtutils/jsonutils.py
bbtutils/timeutils.py
bbtutils-1.0.1.dist-info/METADATA
bbtutils-1.0.1.dist-info/WHEEL
bbtutils-1.0.1.dist-info/top_level.txt
bbtutils-1.0.1.dist-info/RECORD
