Metadata-Version: 2.2
Name: bbtutils
Version: 1.0.1
Summary: private uitls
Author: bbt
Author-email: bbt@example.com
Requires-Dist: cachetools
Requires-Dist: requests
Requires-Dist: pytz
Dynamic: author
Dynamic: author-email
Dynamic: requires-dist
Dynamic: summary
